plotly_click_show/__init__.py
plotly_click_show/frontend/build/asset-manifest.json
plotly_click_show/frontend/build/bootstrap.min.css
plotly_click_show/frontend/build/index.html
plotly_click_show/frontend/build/static/js/main.355053fd.js
plotly_click_show/frontend/build/static/js/main.355053fd.js.LICENSE.txt
plotly_click_show/frontend/build/static/js/main.355053fd.js.map
plotly_click_show-0.1.1.dist-info/LICENSE
plotly_click_show-0.1.1.dist-info/METADATA
plotly_click_show-0.1.1.dist-info/WHEEL
plotly_click_show-0.1.1.dist-info/top_level.txt
plotly_click_show-0.1.1.dist-info/RECORD
